create_jee_paper/__init__.py
create_jee_paper/__main__.py
create_jee_paper/choice_option.py
create_jee_paper/main.py
create_jee_paper/v-test-paper.sty
create_jee_paper-0.2.6.dist-info/METADATA
create_jee_paper-0.2.6.dist-info/WHEEL
create_jee_paper-0.2.6.dist-info/entry_points.txt
create_jee_paper-0.2.6.dist-info/RECORD
